Metadata-Version: 2.4
Name: ScaleHD
Version: 1.3.0
Summary: Automated DNA micro-satellite genotyping.
Home-page: https://github.com/helloabunai/ScaleHD
Author: Alastair Maxwell/University of Glasgow
Author-email: alastair.maxwell@glasgow.ac.uk
License: GPLv3
Keywords: machine-learning genotyping bioinformatics huntington-disease
Classifier: Development Status :: 2 - Pre-Alpha
Classifier: Intended Audience :: Education
Classifier: Intended Audience :: End Users/Desktop
Classifier: Intended Audience :: Science/Research
Classifier: License :: OSI Approved :: GNU General Public License v3 (GPLv3)
Classifier: Programming Language :: Python :: 3.8
Classifier: Environment :: Console
Classifier: Operating System :: MacOS :: MacOS X
Classifier: Operating System :: POSIX
Requires-Python: >=3.8
License-File: LICENSE
Requires-Dist: lxml
Requires-Dist: numpy==2.2.1
Requires-Dist: seaborn
Requires-Dist: matplotlib
Requires-Dist: scikit-learn==1.6.1
Requires-Dist: scipy==1.15.1
Requires-Dist: peakutils
Requires-Dist: pandas
Requires-Dist: pysam==0.22.1
Requires-Dist: regex
Requires-Dist: PyPDF2
Requires-Dist: reportlab
Requires-Dist: generatr==1.0
Requires-Dist: batchadapt==1.2
Requires-Dist: cutadapt==4.9
Requires-Dist: PyVCF3
Requires-Dist: fadapa
Requires-Dist: pytest
Dynamic: author
Dynamic: author-email
Dynamic: classifier
Dynamic: description
Dynamic: description-content-type
Dynamic: home-page
Dynamic: keywords
Dynamic: license
Dynamic: license-file
Dynamic: requires-dist
Dynamic: requires-python
Dynamic: summary
